{
    "version": "0.11.2",
    "architecture": {
        "64bit": {
            "url": "https://github.com/kcl-lang/cli/releases/download/v0.11.2/kcl-v0.11.2-windows-amd64.zip",
            "bin": [
                "kcl.exe"
            ],
            "hash": "048c4a4bc0b4e4ccf3e7509d1cdb2232691551e79a3c7ad6438305f63a1c5ca4"
        },
        "arm64": {
            "url": "https://github.com/kcl-lang/cli/releases/download/v0.11.2/kcl-v0.11.2-windows-arm64.zip",
            "bin": [
                "kcl.exe"
            ],
            "hash": "e797f12e38cf3e10b6d5403df766ae0ef75119b5483adf1d923915c3c2b41101"
        }
    },
    "homepage": "http://github.com/kcl-lang/kcl",
    "license": "Apache License 2.0",
    "description": "KCL Command Line Interface"
}