{
    "version": "0.8.5",
    "architecture": {
        "64bit": {
            "url": "https://github.com/kcl-lang/cli/releases/download/v0.8.5/kcl-v0.8.5-windows-amd64.zip",
            "bin": [
                "kcl.exe"
            ],
            "hash": "5fd56dcbde9b09a82bb0a84535a405cf58bb650b4447c089c2fcd3d6c7e766b9"
        },
        "arm64": {
            "url": "https://github.com/kcl-lang/cli/releases/download/v0.8.5/kcl-v0.8.5-windows-arm64.zip",
            "bin": [
                "kcl.exe"
            ],
            "hash": "9c169b72adae7dd1b706dc3a0a0ba1480b915e236824617eb78704b189b42706"
        }
    },
    "homepage": "http://github.com/kcl-lang/kcl",
    "license": "Apache License 2.0",
    "description": "KCL Command Line Interface"
}