{
    "version": "0.10.0-beta.2",
    "architecture": {
        "64bit": {
            "url": "https://github.com/kcl-lang/cli/releases/download/v0.10.0-beta.2/kcl-v0.10.0-beta.2-windows-amd64.zip",
            "bin": [
                "kcl.exe"
            ],
            "hash": "51aefd25e30b0ea9c4ab8006e2f4942226653b51de12569a3a604eb7716f8fc2"
        },
        "arm64": {
            "url": "https://github.com/kcl-lang/cli/releases/download/v0.10.0-beta.2/kcl-v0.10.0-beta.2-windows-arm64.zip",
            "bin": [
                "kcl.exe"
            ],
            "hash": "818c37fd5f705a503cbac3953e6755aa13fa13465377c4fe477f817dbf5dee2d"
        }
    },
    "homepage": "http://github.com/kcl-lang/kcl",
    "license": "Apache License 2.0",
    "description": "KCL Command Line Interface"
}